univers/__init__.py
univers/arch.py
univers/arch.py.ABOUT
univers/arch.py.NOTICE
univers/bsd-new.LICENSE
univers/debian.py
univers/debian.py.ABOUT
univers/debian.py.NOTICE
univers/gem.py
univers/gem.py.ABOUT
univers/gem.py.NOTICE
univers/gentoo.py
univers/gentoo.py.ABOUT
univers/gentoo.py.NOTICE
univers/intdot.py
univers/maven.py
univers/maven.py.ABOUT
univers/maven.py.NOTICE
univers/nuget.py
univers/nuget.py.ABOUT
univers/nuget.py.NOTICE
univers/py.typed
univers/rpm.py
univers/rpm.py.ABOUT
univers/rpm.py.NOTICE
univers/rpm.py.README
univers/rpm.py.antlir.ABOUT
univers/rpm.py.antlir.LICENSE
univers/rpm.py.antlir.NOTICE
univers/univers_semver.py
univers/utils.py
univers/version_constraint.py
univers/version_range.py
univers/versions.py
univers/conan/__init__.py
univers/conan/errors.py
univers/conan/errors.py.ABOUT
univers/conan/errors.py.NOTICE
univers/conan/version.py
univers/conan/version.py.ABOUT
univers/conan/version.py.NOTICE
univers/conan/version_range.py
univers/conan/version_range.py.ABOUT
univers/conan/version_range.py.NOTICE
univers-31.1.0.dist-info/licenses/AUTHORS.rst
univers-31.1.0.dist-info/licenses/CHANGELOG.rst
univers-31.1.0.dist-info/licenses/CODE_OF_CONDUCT.rst
univers-31.1.0.dist-info/licenses/NOTICE
univers-31.1.0.dist-info/licenses/README.rst
univers-31.1.0.dist-info/licenses/apache-2.0.LICENSE
univers-31.1.0.dist-info/licenses/bsd-new.LICENSE
univers-31.1.0.dist-info/licenses/mit.LICENSE
univers-31.1.0.dist-info/METADATA
univers-31.1.0.dist-info/WHEEL
univers-31.1.0.dist-info/top_level.txt
univers-31.1.0.dist-info/RECORD
