Metadata-Version: 2.4
Name: univers
Version: 31.1.0
Summary: A mostly universal library to parse and compare software package versions and version ranges. A companion to Package URLs.
Home-page: https://github.com/aboutcode-org/univers
Author: Shivam Sandbhor, nexB. Inc. and others
Author-email: info@aboutcode.org
License: Apache-2.0 AND BSD-3-Clause AND MIT
Keywords: semver,utilities,version,release,version range,package URL,purl,arch,pacman,pypi,rpm,gentoo,ebuild,maven,debian,rubygems
Classifier: Development Status :: 5 - Production/Stable
Classifier: Intended Audience :: Developers
Classifier: Programming Language :: Python :: 3
Classifier: Programming Language :: Python :: 3 :: Only
Classifier: Topic :: Software Development
Classifier: Topic :: Utilities
Requires-Python: >=3.8
License-File: apache-2.0.LICENSE
License-File: bsd-new.LICENSE
License-File: mit.LICENSE
License-File: NOTICE
License-File: AUTHORS.rst
License-File: CHANGELOG.rst
License-File: README.rst
License-File: CODE_OF_CONDUCT.rst
Requires-Dist: attrs
Requires-Dist: packaging
Requires-Dist: semantic-version
Requires-Dist: semver
Provides-Extra: testing
Requires-Dist: pytest!=7.0.0,>=6; extra == "testing"
Requires-Dist: pytest-xdist>=2; extra == "testing"
Requires-Dist: aboutcode-toolkit>=7.0.2; extra == "testing"
Requires-Dist: pycodestyle>=2.8.0; extra == "testing"
Requires-Dist: twine; extra == "testing"
Requires-Dist: black; extra == "testing"
Requires-Dist: commoncode; extra == "testing"
Requires-Dist: isort>=5.10.1; extra == "testing"
Provides-Extra: docs
Requires-Dist: Sphinx>=5.0.2; extra == "docs"
Requires-Dist: sphinx-rtd-theme>=1.0.0; extra == "docs"
Requires-Dist: sphinx-reredirects>=0.1.2; extra == "docs"
Requires-Dist: doc8>=0.11.2; extra == "docs"
Requires-Dist: sphinx-autobuild; extra == "docs"
Requires-Dist: sphinx-rtd-dark-mode>=1.3.0; extra == "docs"
Requires-Dist: sphinx-copybutton; extra == "docs"
Dynamic: license-file
